docs/api.md
docs/index.md
docs/requirements.txt
log2me/__init__.py
log2me/__version__.py
log2me/print_loggers.py
log2me/print_loggers_tests.py
log2me/settings.py
log2me/setup_log.py
log2me/setup_log_tests.py
log2me-0.1.0.dist-info/LICENSE
log2me-0.1.0.dist-info/METADATA
log2me-0.1.0.dist-info/WHEEL
log2me-0.1.0.dist-info/top_level.txt
log2me-0.1.0.dist-info/RECORD
